{
  "stories": [
    {
      "title": "Sourcefabric",
      "subtitle": "Senior Web Developer",
      "date": "since 2018",
      "link": "https://www.sourcefabric.org/",
      "image": "/static/images/stories/sourcefabric.jpg"
    },
    {
      "title": "LadJS",
      "subtitle": "Core team member",
      "date": "since 2017",
      "link": "https://github.com/ladjs/lad",
      "image": "/static/images/stories/ladjs.png"
    },
    {
      "title": "Keepcoding",
      "subtitle": "Master in Full Stack Javascript",
      "date": "2017-2018",
      "link":
        "https://keepcoding.io/es/keepcoding-web-development-master-bootcamp/",
      "image": "/static/images/stories/kc.png"
    },
    {
      "title": "StangDS",
      "subtitle": "Web Developer",
      "date": "2016-2017",
      "link": "http://stangds.com/",
      "image":
        "/static/images/stories/stang.png"
    },
    {
      "title": "USC",
      "subtitle": "Computer Science Degree",
      "date": "2011-2015",
      "link": "http://www.usc.es/etse/",
      "image":
        "/static/images/stories/usc.jpg"
    }
  ]
}
